{
  "count": 457,
  "uniques": 278,
  "clones": [
    {
      "timestamp": "2023-05-31T00:00:00Z",
      "count": 70,
      "uniques": 43
    },
    {
      "timestamp": "2023-06-01T00:00:00Z",
      "count": 64,
      "uniques": 40
    },
    {
      "timestamp": "2023-06-02T00:00:00Z",
      "count": 66,
      "uniques": 42
    },
    {
      "timestamp": "2023-06-03T00:00:00Z",
      "count": 63,
      "uniques": 44
    },
    {
      "timestamp": "2023-06-04T00:00:00Z",
      "count": 66,
      "uniques": 37
    },
    {
      "timestamp": "2023-06-05T00:00:00Z",
      "count": 65,
      "uniques": 36
    },
    {
      "timestamp": "2023-06-06T00:00:00Z",
      "count": 63,
      "uniques": 36
    }
  ]
}