{
  "count": 288,
  "uniques": 162,
  "clones": [
    {
      "timestamp": "2022-11-17T00:00:00Z",
      "count": 63,
      "uniques": 36
    },
    {
      "timestamp": "2022-11-18T00:00:00Z",
      "count": 63,
      "uniques": 35
    },
    {
      "timestamp": "2022-11-19T00:00:00Z",
      "count": 62,
      "uniques": 37
    },
    {
      "timestamp": "2022-11-20T00:00:00Z",
      "count": 64,
      "uniques": 31
    },
    {
      "timestamp": "2022-11-21T00:00:00Z",
      "count": 25,
      "uniques": 14
    },
    {
      "timestamp": "2022-11-22T00:00:00Z",
      "count": 5,
      "uniques": 4
    },
    {
      "timestamp": "2022-11-23T00:00:00Z",
      "count": 6,
      "uniques": 5
    }
  ]
}